{
  "title": "阶级斗争的根源在于两个阶级之间",
  "selectedItems": [
    {
      "ItemName": "A",
      "Content": "物质利益的对立"
    },
    {
      "ItemName": "B",
      "Content": "政治立场的不同"
    },
    {
      "ItemName": "C",
      "Content": "思想观念的对立"
    },
    {
      "ItemName": "D",
      "Content": "社会分工的不同"
    }
  ],
  "answer": "A",
  "explain": "🌟嘿，年轻的思想家们！今天咱们聊聊一个超重要的哲学话题——阶级斗争的根源！💥\n\n阶级斗争可是马克思老爷子特意提出来的概念哦，它深刻揭示了社会的“冲突剧场”。😱你知道吗，阶级斗争根源于什么吗？正确答案是：**物质利益的对立**！🤑\n\n想象一下，两个“班级”之间的PK赛👊——一边是大富豪们（上层阶级），另一边是辛苦工作的平民（下层阶级）。富人们想要更多的利益和资源，穷人们则苦苦挣扎，试图改善生活。这就好比在聚会上，有的人吃了个别墅大餐，有的人只是啃面包碎。🥖🍞你觉得，这两种人能和谐相处吗？\n\n所以，物质利益的对立就像一场资源的争夺战，谁都不想让对方赢，最后只能在斗争中找寻出路。因此，阶级斗争就是活生生地展现在我们眼前的现实拼图🔍！\n\n当然，除了物质利益，政治立场、思想观念和社会分工也都有自己的“斗争味道”，但它们存在的根本原因，仍然是为了争取更好的生活和资源💪！\n\n所以，下次在讨论社会问题时，可别忘了这背后的利益对立哦！ 💡\n\n#阶级斗争 #物质利益 #马克思主义 #社会现象 #平民风暴"
}