{
  "title": "两种根本对立的发展观是",
  "selectedItems": [
    {
      "ItemName": "A",
      "Content": "唯物主义和唯心主义"
    },
    {
      "ItemName": "B",
      "Content": "可知论和不可知论"
    },
    {
      "ItemName": "C",
      "Content": "唯物辩证法和形而上学"
    },
    {
      "ItemName": "D",
      "Content": "一元论和二元论"
    }
  ],
  "answer": "C",
  "explain": "🌟嘿小伙伴们，今天我们来聊聊一个很有趣的话题——两种根本对立的发展观！它们分别是“唯物辩证法”和“形而上学”，这可是马克思主义的核心思想哦！😎\n\n先给大家打个比喻：想象你在玩游戏🎮，“唯物辩证法”就像是一个灵活的战士，能够根据环境变化施展各种技能；而“形而上学”就像是一个老古董，固定不变，没法应对场上的变化，结果一遇到强敌就容易被打败！👾\n\n🔥那么，区别在哪里呢？简单来说：\n- 🌍 **唯物辩证法**：强调世界是动态的、不断变化的，事物之间是相互联系、互相作用的。简而言之，就是“变”是常态，变化中有发展🚀。\n- 🐢 **形而上学**：则是看待问题时只注重事物的表面特征，更像是“定步不变”，忽略了事物之间的关系和变化的本质，易于导致片面理解😩。\n\n📚这些观点听起来可能有点鼻血，但它们在生活中无处不在！比如，你的朋友圈中总有一些人固执地认为“成功就是万难克服的那一刻”，而有些人则清楚每一次小的努力和学习都是成功的积累！🤗\n\n所以，考试的话题中，选择C（唯物辩证法和形而上学）就是对的啦！记住，灵活应变才是生活的真理！💪✨\n\n#唯物辩证法 #形而上学 #马克思主义 #哲学小知识 #学习生活"
}