{
  "title": "“一把钥匙开一把锁”,这句话强调的是",
  "selectedItems": [
    {
      "ItemName": "A",
      "Content": "要承认事物的客观性"
    },
    {
      "ItemName": "B",
      "Content": "要承认事物运动的规律性"
    },
    {
      "ItemName": "C",
      "Content": "要注重分析矛盾的普遍性"
    },
    {
      "ItemName": "D",
      "Content": "要注重分析矛盾的特殊性"
    }
  ],
  "answer": "D",
  "explain": "🌟🔑一把钥匙开一把锁，这句话听起来简单，但其实它背后蕴含的哲理可是深奥无比哦！🤓\n\n大家可以把“钥匙”想象成一个解决问题的方法，而“锁”就是我们生活中遇到的各种困难和矛盾。每一种矛盾都有它特定的“锁”，所以我们要用不同的“钥匙”去解锁。💡\n\n这道题其实是在告诉我们：在解决现实问题时，我们不能仅仅依靠一些老套路或固定模式，而是要注重分析矛盾的特殊性！也就是选项D！🌈例如，就像在玩密室逃脱时，不同的房间有不同的线索，你不能用单一的思路去破解每一个房间的谜题。🔍\n\n选择合适的解决方案，正是站在了事物的特殊性上，这样才能更好解锁生活的每一个关卡！💪✨\n\n所以，记得哦，面对复杂的世界，要灵活运用方法，好好分析每一个矛盾的特点，乐观应对每一次挑战！🏆\n\n#马克思主义 #矛盾分析 #特殊性 #知识分享 #趣味学习"
}