{
  "title": "马克思主义认识论的首要的和基本的观点是",
  "selectedItems": [
    {
      "ItemName": "A",
      "Content": "实践的观点"
    },
    {
      "ItemName": "B",
      "Content": "发展的观点"
    },
    {
      "ItemName": "C",
      "Content": "历史的观点"
    },
    {
      "ItemName": "D",
      "Content": "辩证的观点"
    }
  ],
  "answer": "A",
  "explain": "🌟Hey，小伙伴们！今天我们来聊聊一个超级有趣又重要的知识点——马克思主义认识论的首要观点！🎉\n\n大家知道吗？马克思主义认为，最核心的观点就是“实践的观点”！😎✨这就像我们玩游戏一样，光看攻略、看别人的经验是不够的，唯有亲身实践，才能真正掌握游戏的技巧，对不对？🎮\n\n🔍 **知识点分析：**\n1. **实践的重要性**：在马克思的眼里，实践是检验真理的唯一标准。简单来说，就是“我做过，才有发言权！”🙌 只有通过亲身的探索和体验，才能更全面、真实地理解事物。\n  \n2. **与发展的观点的关系**：虽然发展的观点也是很重要的，它强调事物要随着时间和条件的变化而发展。但没有实践，这种发展就像是在空中楼阁，根本没有实在的基础！🏰\n\n3. **历史与辩证**：历史观点和辩证观点都提供了对事物变化的深刻理解，但同样，认识事物的出发点还是得从实践开始，去感知与体验的真实之中！📜\n\n所以，掌握“实践的观点”，就像手握了打开真理大门的金钥匙，走出理论的迷雾，直接通向真实的世界！🔑🌍\n\n快来一起深刻体会一下这个观点，记住：别光会“空谈理论”，一定要动手去“实践”哦！💪✨\n\n#马克思主义 #认识论 #实践的重要性 #年轻人的思考 #探索真理"
}