{
  "title": "下列各项不属于认识客体的是",
  "selectedItems": [
    {
      "ItemName": "A",
      "Content": "已经探测到的引力波"
    },
    {
      "ItemName": "B",
      "Content": "已经揭秘的史前文明"
    },
    {
      "ItemName": "C",
      "Content": "已经观测到的银河系"
    },
    {
      "ItemName": "D",
      "Content": "尚未发现的地下矿"
    }
  ],
  "answer": "D",
  "explain": "🎉小伙伴们，今天来聊聊真假认识客体的那些事儿！🤔\n\n题目问我们：“下列各项不属于认识客体的是哪一项？”让我们来逐一拆解选项吧！\n\n🔍A. 已经探测到的引力波：这是个超级酷的东西！就像科学界的“听力测试”，我们已经通过特殊的设备“听”到了引力波的声音，绝对是认识客体的一部分！✨\n\n🔍B. 已经揭秘的史前文明：这可是历史的瑰宝！考古学家们通过挖掘和研究，揭示了古代人类的生活。我们对史前文明的了解，毫无疑问也是我们的认识客体哦！🗿✨\n\n🔍C. 已经观测到的银河系：宇宙虽然大，但通过天文观测，我们已经“看到了”银河系的壮丽景象。这同样是我们认识的对象之一！🌌🌠\n\n🔍D. 尚未发现的地下矿：好吧，这一项有点特别哦。它就像是在寻找隐藏的宝藏，但由于我们还没有发现这些地下矿资源，所以它不属于认识客体！😅💎\n\n综上所述，选项D是正确答案！在科学探索的旅程中，认识客体就像是我们生活中的各种发现，已经被探明的，才能纳入我们的知识库。🏆\n\n希望这次的解析能够帮助你加深理解，如果你也觉得这个话题有趣，快来分享给朋友们吧！🤗\n\n#认识客体 #引力波 #史前文明 #银河系 #知识分享 🌟"
}