{
  "title": "两条根本对立的认识路线是",
  "selectedItems": [
    {
      "ItemName": "A",
      "Content": "可知论和不可知论"
    },
    {
      "ItemName": "B",
      "Content": "唯物主义反映论和唯心主义先验论"
    },
    {
      "ItemName": "C",
      "Content": "主观唯心主义认识论和客观唯心主义认识论"
    },
    {
      "ItemName": "D",
      "Content": "能动革命的反映论和直观被动的反映论"
    }
  ],
  "answer": "B",
  "explain": "✨嘿，亲爱的小伙伴们！今天我们来聊聊马克思主义认识论中的“对立路线”~ 这可是个特别有趣的话题哦，快速跟上，别走神~ 🚀\n\n首先，咱们要知道，认识论就是研究知识来源和获取方式的学问，举个例子，就像你去咖啡店点咖啡，一杯好咖啡的味道取决于你选的豆子和冲泡的方法☕️！而在这里，有两条根本对立的认识路线，咱们选择的是：**唯物主义反映论和唯心主义先验论** （选项B）！📚\n\n### 知识点分析：\n1. **唯物主义反映论**：这个观点就像是在说“世界是客观存在的，我们的知识是对这个世界的反映”。比如你在草地上看到小狗，那你大脑里的形象是根据真实小狗来的，真真实实的🐶。\n\n2. **唯心主义先验论**：而此时，唯心主义好比在说“世界只存在于我们的认知中，外部世界不一定真实”，想象一下《黑客帝国》里的莫菲斯，他一直在问“你能相信你眼前所看到的一切吗？”🙃\n\n这两条路线，简直像是一场认知的“跨界大战”！唯物主义认为我们的知识取决于外部世界；而唯心主义则认为是一切来自于\"心\"。这就像是有的人信仰“看得到才是真理”，有的人则觉得“感觉就是一切”！\n\n### 现代比喻：\n想象一下，我们在玩虚拟现实游戏🎮，唯物主义就是你在游戏中真的能感受到的每一次跳跃和碰撞，而唯心主义则是你必须相信这些虚拟的瞬间是你自己脑海中也存在的真实感受。两者各有千秋，但却是背道而驰的！🤔\n\n所以，想要解开这个神秘的知识迷雾，了解唯物主义反映论和唯心主义先验论之间的区别，就显得尤为重要咯~ \n\n希望这趟知识的旅程让你们更清晰地理解了这个话题，继续加油哦！💪💖\n\n#马克思主义 #认识论 #唯物主义反映论 #唯心主义先验论 #知识分享"
}