{
  "title": "劳动不再是一种谋生手段、而成为人们生活第一需要的社会是",
  "selectedItems": [
    {
      "ItemName": "A",
      "Content": "社会主义社会"
    },
    {
      "ItemName": "B",
      "Content": "共产主义社会"
    },
    {
      "ItemName": "C",
      "Content": "资本主义社会"
    },
    {
      "ItemName": "D",
      "Content": "信息社会"
    }
  ],
  "answer": "B",
  "explain": "🌟嘿，宝贝们！今天咱们来聊聊一个超级有趣的题目，啥？就是“劳动不再是一种谋生手段，而成为人们生活第一需要的社会是？”🤔\n\n首先，咱们要看选项：\n\nA: 社会主义社会  \nB: 共产主义社会 ✅  \nC: 资本主义社会  \nD: 信息社会\n\n如果把社会形态比作不同的音乐风格，那社会主义就像是温柔的民谣，资本主义则有点像电音轰炸。而共产主义就像是一场狂欢派对，大家都在享受音乐和舞蹈，不为生活奔波🍾💃。在这个派对上，劳动不再是为了生存，而是为了感受生活的快乐，真的是每个人的生活第一需要！\n\n🎉 在共产主义社会里，劳动被视为自我实现、创造价值的一种方式。想象一下，你最喜欢的事情不再是为了交房租，而是因为热爱！🤗 这就好比你追着自己的梦想，不为物质所困，生活充满活力和乐趣。\n\n🔍 知识点分析：\n- **劳动**：在不同社会中，劳动的意义和目的会发生变化。在资本主义社会，劳动多是为了赚钱；而在共产主义社会，劳动体现个体价值，成为个人生活的核心。\n- **生活需求**：随着社会的发展，人们对生活质量的期望提高，生活的基本需求转变为精神需求。\n\n所以，正确答案是 B: 共产主义社会！✨\n\n快来和我一起转发这份小知识，让更多的小伙伴了解劳动的真正意义吧！💬❤️\n\n#马克思主义原理 #共产主义 #劳动价值 #生活需求 #知识分享"
}