{
  "title": "把社会主义本质概括为“解放生产力，发展生产力，消灭剥削，消除两极分化，最终达到共同富裕”的中国共产党人是",
  "selectedItems": [
    {
      "ItemName": "A",
      "Content": "毛泽东"
    },
    {
      "ItemName": "B",
      "Content": "刘少奇"
    },
    {
      "ItemName": "C",
      "Content": "周恩来"
    },
    {
      "ItemName": "D",
      "Content": "邓小平"
    }
  ],
  "answer": "D",
  "explain": "🌟小伙伴们，今天我们来聊聊一个超级重要的马克思主义概念——社会主义的本质！🤓✨\n\n在我们现代生活中，想象一下一个拼团购物的场景，大家把资源聚在一起，共同享受更低的价格，快快乐乐的买买买！这就是我们追求的“共同富裕”的概念，而这背后也是社会主义的核心要义！🍇🛒\n\n社会主义的本质可以用这几个关键词概括：**解放生产力、发展生产力、消灭剥削、消除两极分化，最终实现共同富裕**。让我来给你们拆解一下哦！🔍\n\n1️⃣ **解放生产力**：就像给手机充电一样，让它们释放出更大的能量去工作，生产力也是如此，必须放开手脚，充分发挥！\n\n2️⃣ **发展生产力**：这部分可以想象成升级换代，比如把我们的小白机换成最新款的智能手机，科技进步，生产效率嗖嗖的提升！📱🚀\n\n3️⃣ **消灭剥削**：就像拒绝过分“吃瓜”的朋友，大家都要平等分享资源，不能让个别人的嘴巴永远在“吃”，其他人却只能看! 🙅‍♂️🍉\n\n4️⃣ **消除两极分化**：想象一下，如果大家的年收入差距越来越大，那可是让“贫富差距”这个怪兽越来越壮大！我们要让人人都能享有生活的美好，而不是让一小撮人独享资源。同舟共济，才是我们的大方向！🚣‍♀️💕\n\n最后，经过我们一系列的分析，你们知道是谁提出了这么系统的社会主义理念吗？那就是我们伟大的邓小平同志！他强调发展生产力是社会主义的根本任务，真的是非常有远见哦！🌈🌟\n\n所以，选项中正确答案就是 **D：邓小平**！💡👏\n\n希望这堂小课能让大家对社会主义的本质有更深入的理解！点赞支持转发哦，我们下一课再见！💖✌️\n\n#社会主义 #马克思主义 #邓小平 #共同富裕 #生产力"
}