{
  "title": "“生活、实践的观点，应该是认识论的首要的和基本的观点”的提出者是",
  "selectedItems": [
    {
      "ItemName": "A",
      "Content": "马克思"
    },
    {
      "ItemName": "B",
      "Content": "恩格斯"
    },
    {
      "ItemName": "C",
      "Content": "列宁"
    },
    {
      "ItemName": "D",
      "Content": "毛泽东"
    }
  ],
  "answer": "C",
  "explain": "🎉✨小伙伴们，今天我们来聊聊一个热点知识点，直接上题目：“生活、实践的观点，应该是认识论的首要的和基本的观点”，这个观点是谁提出的呢？🤔\n\n🚀 选项是：\nA: 马克思  \nB: 恩格斯  \nC: 列宁  \nD: 毛泽东  \n\n答案是C：列宁！🎉\n\n那么，为什么列宁会强调生活和实践的重要性呢？让我们用一个超简单的比喻来理解。想象一下，你在玩一款新游戏🎮，你阅读了所有的攻略📚，但如果不亲自去玩，在游戏中失误、尝试、探索，你是不是永远无法真正掌握这款游戏？所以，只靠理论是不够的，实践才是“真理”的试金石！🔍\n\n💡 列宁认为，实践是认识的源泉，真实的生活才是我们获取知识的基础。他强调，只有通过实践，我们才能检验、修正和深化我们的认识，这就像在生活中不断“打怪升级”！⚔️ 每一次尝试和错误都是我们成长的宝贵经验。💪\n\n所以，记住，生活和实践才是认识论的根基哦！现在，你是不是觉得这个观点变得更加易懂了呢？快把这个干货分享给你的朋友吧！✌️\n\n#认识论 #实践重要性 #列宁 #马克思主义 #知识分享"
}