{
  "title": "认识的源泉、动力、标准和最终目的是",
  "selectedItems": [
    {
      "ItemName": "A",
      "Content": "实践"
    },
    {
      "ItemName": "B",
      "Content": "理想"
    },
    {
      "ItemName": "C",
      "Content": "真理"
    },
    {
      "ItemName": "D",
      "Content": "经验"
    }
  ],
  "answer": "A",
  "explain": "🎉 Hey，小伙伴们！今天我们来聊聊认识的源泉、动力、标准和最终目的是什么！希望能让你们在备考的时候轻松一点哦！🌟\n\n📚 首先，咱们先来捋捋这个题目。题目问到的是“认识”的四个方面，听起来有点抽象，但其实就像我们在玩游戏，知道了每个角色的特性，才能轻松过关！👍\n\n💡 **认识的源泉：实践** \n想象一下，假如你是一位厨师，要做出一道美味的菜肴，你的灵感（认识）少不了来自平时的实践哦！这是因为只有通过实践，才能体验到食材的搭配、火候的掌握、调味的秘诀。而在马克思主义中，实践是认识的源泉，只有通过不断的实践，我们才能不断累积知识，进行反思和总结！🍳✨\n\n🔋 **认识的动力：实践也是动力！** \n就像你玩喜欢的游戏，完成任务后得到了奖励，那种成就感让你更想继续玩下去！在现实生活中，实践带来的反馈和体验也能激发我们更深入的探索和思考，推动我们不断前行！🌈\n\n⚖️ **认识的标准与最终目的** \n相信我们都想知道什么才是真理，对吧？在马克思主义的框架中，实践被认为是检验真理的唯一标准，最终目的就是为了推动社会发展，实现人与自然的和谐共处。当我们把生活与理论结合，才能真正创造出更好的未来！🌍❤️\n\n所以，综合这四点，我们发现实践真的是认识的小宇宙，源泉、动力、标准和最终目的，统统离不开它！✨\n\n💖 好啦，小伙伴们，记得把🎯这个知识点好好消化，必定在考试中大放异彩哦！未来就是你们的舞台！加油！💪\n\n#马克思主义 #认识论 #实践第一 #考前必备 #学习有趣"
}