{
  "AllTestID": 80830164,
  "ATestID": 80830164,
  "Difficulty": "",
  "BookTestNo": "182",
  "Title": "20世纪二三十年代活跃着的中间党派的社会基础主要是",
  "Explain": "在20世纪二三十年代的中国，社会上可是热闹非凡，尤其是中间党派的崛起，简直就像是一场政治大Party！🎉 这时候，民族资产阶级和上层小资产阶级，还有知识分子们，纷纷站到了这个舞台上，成为了中间党派的强大社会基础。\n\n首先，民族资产阶级就像是那群刚刚创业的小老板，他们希望在这个动荡的时代，找到自己的立足之地。想象一下，今天的创业青年们，面临着困难和挑战，但依然渴望发展，这就是当时的民族资产阶级啊！他们希望通过参与政治，争取更多的权利和利益。\n\n再来说说上层小资产阶级，想象一下那些时髦的咖啡馆老板和小商店主，他们有一定的经济基础，但又不想和大资本家们同流合污，想要在社会上有一席之地。他们的声音被中间党派所吸引，因为这可以帮助他们发声，争取自己的权利。☕️\n\n最后，知识分子们就像是现代社会的“意见领袖”，他们对社会的不满和对未来的憧憬让他们积极参与政治。他们不仅仅是书本上的理论家，更是希望通过行动改变社会的一群人。📚✨\n\n所以，20世纪的中间党派，背后有着这样一群充满活力、追求变革的人，他们共同推动了历史的进程。就像今天的年轻人们，勇敢追梦、敢于发声，我们也在为自己的未来而奋斗！💪🚀",
  "Type": "ATEST",
  "SubType": "单选题",
  "SelectedItems": [
    {
      "ItemName": "A",
      "Content": "工农阶级和上层小资产阶级及其知识分子"
    },
    {
      "ItemName": "B",
      "Content": "大地主资产阶级和民族小资产阶级"
    },
    {
      "ItemName": "C",
      "Content": "工农阶级和大地主资产阶级"
    },
    {
      "ItemName": "D",
      "Content": "民族资产阶级和上层小资产阶级及其知识分子"
    }
  ],
  "Answer": "D",
  "TestPoint": "",
  "IsFav": 0,
  "UserNoteContent": "",
  "StyleID": 452366,
  "From": "",
  "ChapterID": -1,
  "UserID": 1063943,
  "TestID": 80830164,
  "HistoricalDate": {
    "year": 1920,
    "month": null,
    "day": null
  }
}