{
  "AllTestID": 80830222,
  "ATestID": 80830222,
  "Difficulty": "",
  "BookTestNo": "240",
  "Title": "1938年初,担任国民政府军...事委员会政治部副部长的是",
  "Explain": "在1938年这个波澜壮阔的历史节点上，国民政府军事委员会的政治部副部长居然是周恩来！🤯 可能很多小伙伴对这个名字并不陌生，他可是后来的国家总理，翻开历史的书卷，他的身影闪耀在中国现代史的舞台上。\n\n说到周恩来，大家可能会想起他那种淡定从容的气质，仿佛无论风云变幻，他总能稳住阵脚。就像是当今的“冷静应对危机”的职场达人，他在那个动荡的年代，带领团队面对各种挑战，处理复杂的政治局势，真的是“职场老将”啊！💼✨\n\n知识点分析一下：1938年，中国正处于抗日战争的关键时期，国民政府需要一位既有政治智慧，又有组织能力的人来协调军政关系。而周恩来恰好就是这样的人，他不仅在政治上有深厚的积累，在军事上也颇有见地，可以说是那个时代的“全能型人才”。💪\n\n所以，周恩来在1938年担任政治部副部长，不仅是他个人职业生涯的一个重要转折点，也是中国历史上一个不容忽视的里程碑！想象一下，如果没有周恩来的智慧和勇气，历史可能会有很大的不同呢！🌟\n\n历史从来不是单一的线条，而是一个个精彩的瞬间交织而成的。今天我们回顾这一段历史，希望大家都能从中汲取智慧，勇敢面对生活中的挑战！💖",
  "Type": "ATEST",
  "SubType": "单选题",
  "SelectedItems": [
    {
      "ItemName": "A",
      "Content": "张治中"
    },
    {
      "ItemName": "B",
      "Content": "何应钦"
    },
    {
      "ItemName": "C",
      "Content": "周恩来"
    },
    {
      "ItemName": "D",
      "Content": "林伯渠"
    }
  ],
  "Answer": "C",
  "TestPoint": "",
  "IsFav": 0,
  "UserNoteContent": "",
  "StyleID": 452366,
  "From": "",
  "ChapterID": -1,
  "UserID": 1063943,
  "TestID": 80830222,
  "HistoricalDate": {
    "year": 1938,
    "month": null,
    "day": null
  }
}