{
  "AllTestID": 81567632,
  "ATestID": 81567632,
  "Difficulty": "",
  "BookTestNo": "286",
  "Title": "解放区军民粉碎国民党军     队的重点进攻是在",
  "Explain": "嘿，小伙伴们！今天我们来聊聊那个激动人心的历史时刻——解放区军民粉碎国民党军队的重点进攻，时间就定在1947年6月！🎉\n\n想象一下，当时的中国就像一场超级紧张的比赛，解放军就像是场上奋勇拼搏的选手，而国民党军队则是个强劲的对手，双方都在为胜利而斗争，气氛可真是紧张刺激啊！⚔️\n\n1947年6月，解放军展现了超强的团结和战斗力，像是一支训练有素的电竞战队，配合默契，策略灵活，最终在战场上取得了决定性的胜利。这场战斗不仅是对敌军的有力打击，更是为后来的解放事业奠定了坚实的基础。💪\n\n知识点来啦！这次战斗的胜利不仅是军事上的成就，更是民心所向。解放区的军民齐心协力，充分展现了人民战争的力量，这一点在历史上可是大名鼎鼎的哦！它告诉我们，团结就是力量，无论是在战场上，还是在我们的日常生活中，只要大家齐心协力，就一定能战胜困难！🌟\n\n所以，了解历史不仅仅是为了记住那些曾经的事，更是为了从中汲取力量，激励我们在生活中勇往直前！✨希望你们喜欢这段历史故事，下次我们再一起探索更多有趣的历史吧！",
  "Type": "ATEST",
  "SubType": "单选题",
  "SelectedItems": [
    {
      "ItemName": "A",
      "Content": "1947年3月"
    },
    {
      "ItemName": "B",
      "Content": "1947年4月"
    },
    {
      "ItemName": "C",
      "Content": "1947年6月"
    },
    {
      "ItemName": "D",
      "Content": "1947年7月"
    }
  ],
  "Answer": "C",
  "TestPoint": "",
  "IsFav": 0,
  "UserNoteContent": "",
  "StyleID": 452366,
  "From": "",
  "ChapterID": -1,
  "UserID": 1063943,
  "TestID": 81567632,
  "HistoricalDate": {
    "year": 1946,
    "month": null,
    "day": null
  }
}