{
  "AllTestID": 81567661,
  "ATestID": 81567661,
  "Difficulty": "",
  "BookTestNo": "315",
  "Title": "毛泽东向全世界宣告:“占人类总数四分之一的中国人从此站立起来了”,是在",
  "Explain": "大家好呀！今天我们来聊聊一个超级重要的历史瞬间，那就是毛泽东在中国人民政治协商会议第一届全体会议上发表的那句经典话：“占人类总数四分之一的中国人从此站立起来了！”这句话不仅是一种宣言，更是一种时代的象征！✨\n\n想象一下，就像你在班级中默默无闻，突然有一天站出来，大声说出自己的想法！这种感觉既激动又充满力量！💪 1949年，毛泽东站在历史的舞台上，向全世界宣告中国人民的崛起，那一刻，仿佛整个中华民族的骄傲都在他的声音中回响。\n\n知识点分析：这句话是在1949年9月21日的中国人民政治协商会议第一届全体会议上讲的，标志着新中国的成立，意味着中国人民从此不再受外来压迫，开始了独立自主的新生活。🌍 就像一位年轻的创业者，经过无数次的失败，终于在某一天成功站上舞台，获得了属于自己的掌声与认可！\n\n通过这句话，毛泽东不仅表达了中国人民的自信与团结，也向世界展示了中国的决心。可以说，这不仅是一个政治宣言，更是中国人民精神面貌的体现！❤️\n\n所以，每次看到这句话，我们都能感受到那股历史的洪流，仿佛能听到那个时代人们心中澎湃的激情。历史从来不是冷冰冰的，它就像一部大电影，每一个瞬间都充满了故事与情感！🎬\n\n希望大家在了解这段历史的同时，也能感受到那份热血与骄傲！让我们继续站立起来，书写属于我们自己的历史吧！💖",
  "Type": "ATEST",
  "SubType": "单选题",
  "SelectedItems": [
    {
      "ItemName": "A",
      "Content": "中华人民共和国开国大典上"
    },
    {
      "ItemName": "B",
      "Content": "中国人民政治协商会议第一届全体会议开幕词中"
    },
    {
      "ItemName": "C",
      "Content": "(论人民民主专政》中"
    },
    {
      "ItemName": "D",
      "Content": "中国人民政治协商会议第一届全体会议闭幕词中"
    }
  ],
  "Answer": "B",
  "TestPoint": "",
  "IsFav": 0,
  "UserNoteContent": "",
  "StyleID": 452366,
  "From": "",
  "ChapterID": -1,
  "UserID": 1063943,
  "TestID": 81567661,
  "HistoricalDate": {
    "year": 1949,
    "month": null,
    "day": null
  }
}