{
  "AllTestID": 81579460,
  "ATestID": 81579460,
  "Difficulty": "",
  "BookTestNo": "386",
  "Title": "毛泽东在《论十大关系》中提出,处理中国共产党和民主党派关系的方针是",
  "Explain": "嘿，亲爱的小伙伴们！今天我们来聊聊一个历史上的大人物——毛泽东，以及他在《论十大关系》中提到的一个非常重要的方针：处理中国共产党和民主党派关系的原则是“长期共存，互相监督”。👀\n\n首先，什么是“长期共存，互相监督”呢？想象一下，咱们的社会就像是一个大舞台，各种乐器齐奏。如果只有一种乐器在演奏，那可真是单调得让人打瞌睡！🎻🎺\n\n毛泽东提到的这个方针，其实就是希望中国共产党和各民主党派能够像一支和谐的乐队，各自发挥特长，互相配合。长期共存意味着大家要一起走得长远，互相监督则是说在这个过程中，要有一个良好的沟通和监督机制，以确保每个乐器都在正确的节拍上🎶。\n\n知识点分析：这个方针的提出，不仅反映了当时中国社会的复杂性，也表达了对多元政治体系的一种探索。通过互相监督，各党派之间能够形成一种健康的竞争关系，避免出现独裁或是极端化的现象，就像是在一个团队中，大家互相帮助、共同进步，才能走得更远！💪\n\n所以，下次提到毛泽东和《论十大关系》时，别忘了这个超级重要的方针哦！它不仅仅是历史的回顾，更是现代社会如何和谐共存的启示！✨",
  "Type": "ATEST",
  "SubType": "单选题",
  "SelectedItems": [
    {
      "ItemName": "A",
      "Content": "长期共存.互相监督"
    },
    {
      "ItemName": "B",
      "Content": "以诚相待.患难与共"
    },
    {
      "ItemName": "C",
      "Content": "肝胆相照.荣辱与共"
    },
    {
      "ItemName": "D",
      "Content": "同甘共苦.同舟共济"
    }
  ],
  "Answer": "A",
  "TestPoint": "",
  "IsFav": 0,
  "UserNoteContent": "",
  "StyleID": 452366,
  "From": "",
  "ChapterID": -1,
  "UserID": 1063943,
  "TestID": 81579460,
  "HistoricalDate": {
    "year": 1961,
    "month": null,
    "day": null
  }
}