{
  "AllTestID": 81579532,
  "ATestID": 81579532,
  "Difficulty": "",
  "BookTestNo": "458",
  "Title": "香港、澳门的回归使…………的构想变为现实。",
  "Explain": "🎉 大家好呀，今天咱们聊聊一个超级重要的历史时刻——香港和澳门的回归！这可是让我们国家在国际舞台上展现自信的一次大行动哦！💪\n\n想象一下，如果把国家比作一位时尚达人，香港和澳门就像是她的两件独特的配饰。虽然它们的风格各自不同，但都在为整个造型增添色彩。在90年代，随着香港和澳门的回归，这位时尚达人终于找到了完美的搭配方式——那就是“一国两制”！🌈\n\n那么，什么是“一国两制”呢？简单来说，就是在同一个国家的框架下，给予香港和澳门更大的自主权，保持它们原有的社会制度和生活方式。就像是在一个大家庭里，哥哥和妹妹虽然有自己的兴趣爱好，但依然共享温暖的家庭氛围。🏠\n\n这一构想的实现，不仅让香港和澳门的居民在回归后能继续享受他们熟悉的生活方式，也让整个国家在多元化发展中展现出强大的包容力。就像是一个人同时能穿着休闲装和正式服装，既能应对朋友聚会，又能参加重要的商务会议。👗👔\n\n所以说，香港和澳门的回归不仅是历史的转折点，更是“一国两制”伟大构想的生动体现。让我们一起期待，未来在这条多元发展的道路上，能够谱写出更多精彩的篇章吧！🎶✨",
  "Type": "ATEST",
  "SubType": "单选题",
  "SelectedItems": [
    {
      "ItemName": "A",
      "Content": "和平统一"
    },
    {
      "ItemName": "B",
      "Content": "一国两制"
    },
    {
      "ItemName": "C",
      "Content": "改革开放"
    },
    {
      "ItemName": "D",
      "Content": "计划生育"
    }
  ],
  "Answer": "B",
  "TestPoint": "",
  "IsFav": 0,
  "UserNoteContent": "",
  "StyleID": 452366,
  "From": "",
  "ChapterID": -1,
  "UserID": 1063943,
  "TestID": 81579532,
  "HistoricalDate": {
    "year": 1997,
    "month": null,
    "day": null
  }
}