{
  "AllTestID": 81579615,
  "ATestID": 81579615,
  "Difficulty": "",
  "BookTestNo": "541",
  "Title": "2001年,中国对外开放进入一个新阶段的标志是",
  "Explain": "在2001年，中国对外开放的脚步迈入了一个全新的时代，而这个标志性的瞬间就是——中国正式加入了世界贸易组织（WTO）！🎉\n\n想象一下，WTO就像是一个全球的超级市场，里面汇聚了来自世界各地的“商家”，每个国家都可以在这里自由交易、互相合作。而中国加入WTO，就像是一个拥有巨大潜力的新店铺，终于打开了大门，向世界展示它的商品和服务。🌍✨\n\n加入WTO意味着中国的市场进一步向外开放，这不仅为中国的企业带来了更多的机遇，也让外国企业能够更方便地进入中国市场。就像是一个年轻的创业者，拿到了入驻大型电商平台的资格，瞬间曝光率大增，顾客也纷纷涌入！📈\n\n在这个新阶段，中国开始参与到国际贸易规则的制定中，逐渐影响着全球经济的走向。不仅如此，国内的消费者也因为各种进口商品的丰富选择而感到开心，生活品质大大提升！🎁\n\n总之，2001年中国加入WTO，不仅是历史的一小步，更是经济腾飞的一大步！我们今天所享受的国际化生活，正是这一重要时刻的结果哦！💪💖",
  "Type": "ATEST",
  "SubType": "单选题",
  "SelectedItems": [
    {
      "ItemName": "A",
      "Content": "加入世界贸易组织"
    },
    {
      "ItemName": "B",
      "Content": "设立海南经济特区"
    },
    {
      "ItemName": "C",
      "Content": "开发和开放上海浦东新区"
    },
    {
      "ItemName": "D",
      "Content": "开放十四个沿海港口城市"
    }
  ],
  "Answer": "A",
  "TestPoint": "",
  "IsFav": 0,
  "UserNoteContent": "",
  "StyleID": 452366,
  "From": "",
  "ChapterID": -1,
  "UserID": 1063943,
  "TestID": 81579615,
  "HistoricalDate": {
    "year": 2001,
    "month": null,
    "day": null
  }
}