{
  "customTestID": "609412342772951900",
  "AllTestID": 303808269,
  "ATestID": 303808269,
  "Difficulty": "easy",
  "BookTestNo": "14",
  "Title": "中华人民共和国的成立，标志着中国进入      。",
  "Explain": "嘿小伙伴们！今天我们来聊聊一个超级重要的历史时刻——中华人民共和国的成立！🎉\n\n1949年10月1日，毛主席在天安门城楼上宣布了新中国的成立，这一刻就像是给中国这辆“慢车”加上了火箭助推器，瞬间从“旧时代”驶入了“新民主主义社会”的快车道！🚄💨\n\n那么，什么是新民主主义社会呢？简单来说，这就像是一个全新的“社交平台”，不同于以往的封建专制。新民主主义社会旨在让各个阶层的人们——农民、工人、知识分子等，都能在这个新平台上发声，参与国家的建设，大家一起“合唱”出美好的未来！🎶\n\n知识点分析一下，这个新社会的建立意味着中国要摆脱帝国主义的控制，走向独立与自强。就像是一个曾经被霸凌的孩子，终于找到了自己的小伙伴，勇敢地站出来为自己发声，开启了崭新的校园生活！💪\n\n所以，中华人民共和国的成立，不只是一纸文书，更是一场伟大的社会革命，让每一个中国人都能在这个新的舞台上追梦、追求幸福！✨\n\n历史的车轮滚滚向前，咱们一起铭记这一重要时刻，期待未来的更多精彩吧！🚀",
  "Type": "ATEST",
  "SubType": "单选题",
  "SelectedItems": [
    {
      "ItemName": "A",
      "Content": "资本主义社会"
    },
    {
      "ItemName": "B",
      "Content": "社会主义初级阶段"
    },
    {
      "ItemName": "C",
      "Content": "新民主主义社会"
    },
    {
      "ItemName": "D",
      "Content": "社会主义高级阶段"
    }
  ],
  "Answer": "C",
  "TestPoint": "",
  "IsFav": 0,
  "UserNoteContent": "",
  "StyleID": 452366,
  "From": "",
  "ChapterID": -1,
  "UserID": 1063943,
  "TestID": 303808269,
  "HistoricalDate": {
    "year": 1949,
    "month": null,
    "day": null
  }
}