{
  "customTestID": "199530249771506680",
  "AllTestID": 303808299,
  "ATestID": 303808299,
  "Difficulty": "easy",
  "BookTestNo": "44",
  "Title": "1962年初，中共中央在北京召开扩大的中央工作会议，总结经验教训，明确工作方向这次会议是      。",
  "Explain": "嘿，年轻的小伙伴们！今天我们来聊聊历史上的一场重量级会议——1962年的“七千人大会”！🎉\n\n想象一下，如果现在有一场聚会，邀请了7000个朋友来分享彼此的经验和教训，那场面可想而知有多热闹！这就是当时中共中央在北京召开的会议，汇聚了各地的干部和代表，目的是为了总结过去几年的经验，特别是大跃进时期的教训。📈\n\n在这个会议上，大家不仅分享了自己的故事，还一起探讨了未来的发展方向。这就像我们现在的团队会议，大家围坐一起，畅所欲言，彼此启发，寻找解决问题的办法。💡\n\n“七千人大会”不仅是一个名字，更是一个历史的转折点！它让人们意识到，集体智慧是多么的重要，只有通过开放的交流，才能找到更好的发展道路。这种精神在今天依然适用哦！🤝\n\n所以，下次你在团队中分享自己的想法时，记得这场历史会议的意义！我们每个人的声音都是宝贵的，正是这些声音汇聚在一起，才能创造出更美好的未来！✨",
  "Type": "ATEST",
  "SubType": "单选题",
  "SelectedItems": [
    {
      "ItemName": "A",
      "Content": "武昌会议"
    },
    {
      "ItemName": "B",
      "Content": "庐山会议"
    },
    {
      "ItemName": "C",
      "Content": "“七千人大会”"
    },
    {
      "ItemName": "D",
      "Content": "亚非会议"
    }
  ],
  "Answer": "C",
  "TestPoint": "",
  "IsFav": 0,
  "UserNoteContent": "",
  "StyleID": 452366,
  "From": "",
  "ChapterID": -1,
  "UserID": 1063943,
  "TestID": 303808299,
  "HistoricalDate": {
    "year": 1962,
    "month": null,
    "day": null
  }
}