{
  "customTestID": "853062103334734790",
  "AllTestID": 303808311,
  "ATestID": 303808311,
  "Difficulty": "easy",
  "BookTestNo": "56",
  "Title": "中国历史上第一部具有资产阶级共和国宪法性质的法典是      。",
  "Explain": "小伙伴们，今天我们要聊聊一部在中国历史上超重要的法典——《中华民国临时约法》！🎉\n\n想象一下，1912年，清朝的皇帝刚刚退位，大家都在憧憬一个崭新的未来。这时候，一群充满理想的人们决定制定一个新的法律框架，就像现在的年轻人一起开会 brainstorm 新的创业点子一样！💡\n\n《中华民国临时约法》可以说是中国历史上第一部具有资产阶级共和国宪法性质的法典。它就像是一张“新时代的通行证”，为当时的中国打下了民主政治的基础。想象一下，如果没有这部法典，咱们的国家可能就像没有GPS的旅行，迷失在历史的迷雾中！🗺️\n\n这部法典规定了很多重要的内容，比如国家的基本结构、政府的职能，甚至还保障了公民的基本权利。它的出现，标志着中国从封建社会向现代国家的转型，就像我们今天从传统的社交方式转向网络社交一样，都是时代的进步！📱\n\n所以，下一次当你听到《中华民国临时约法》，别忘了它在中国历史上的重要性哦！它不仅是法律的奠基石，更是中国人民追求民主与自由的象征！✊✨",
  "Type": "ATEST",
  "SubType": "单选题",
  "SelectedItems": [
    {
      "ItemName": "A",
      "Content": "《中华民国约法》"
    },
    {
      "ItemName": "B",
      "Content": "《中华民国宪法》"
    },
    {
      "ItemName": "C",
      "Content": "《钦定宪法大纲》"
    },
    {
      "ItemName": "D",
      "Content": "《中华民国临时约法》"
    }
  ],
  "Answer": "D",
  "TestPoint": "",
  "IsFav": 0,
  "UserNoteContent": "",
  "StyleID": 452366,
  "From": "",
  "ChapterID": -1,
  "UserID": 1063943,
  "TestID": 303808311,
  "HistoricalDate": {
    "year": 1912,
    "month": null,
    "day": null
  }
}